<annotation>
	<folder>train</folder>
	<filename>163.jpg</filename>
	<path>/home/hamza/ObjectDetection/data/train/163.jpg</path>
	<source>
		<database>Unknown</database>
	</source>
	<size>
		<width>768</width>
		<height>511</height>
		<depth>3</depth>
	</size>
	<segmented>0</segmented>
	<object>
		<name>sleep</name>
		<pose>Unspecified</pose>
		<truncated>0</truncated>
		<difficult>0</difficult>
		<bndbox>
			<xmin>5</xmin>
			<ymin>141</ymin>
			<xmax>382</xmax>
			<ymax>509</ymax>
		</bndbox>
	</object>
	<object>
		<name>sleep</name>
		<pose>Unspecified</pose>
		<truncated>0</truncated>
		<difficult>0</difficult>
		<bndbox>
			<xmin>335</xmin>
			<ymin>139</ymin>
			<xmax>675</xmax>
			<ymax>508</ymax>
		</bndbox>
	</object>
</annotation>
